LICENSE
MANIFEST.in
README.md
setup.py
snnusdk/__init__.py
snnusdk/base.py
snnusdk/campus.py
snnusdk/configs.py
snnusdk/exceptions.py
snnusdk/libiary.py
snnusdk/message.py
snnusdk/room.py
snnusdk/urp.py
snnusdk.egg-info/PKG-INFO
snnusdk.egg-info/SOURCES.txt
snnusdk.egg-info/dependency_links.txt
snnusdk.egg-info/requires.txt
snnusdk.egg-info/top_level.txt
snnusdk/tool/GUI.py
snnusdk/tool/Image.py
snnusdk/tool/Table.py
snnusdk/tool/__init__.py
snnusdk/utils/__init__.py
snnusdk/utils/captcha/__init__.py
snnusdk/utils/captcha/base.py
snnusdk/utils/captcha/urp/__init__.py
snnusdk/utils/captcha/urp/captcha_getter.py
snnusdk/utils/captcha/urp/urp_captcha.py