Metadata-Version: 2.1
Name: snnusdk
Version: 0.0.2
Summary: SNNU Python-SDK for humans
Home-page: https://github.com/ZhaoQi99/SNNU-SDK
Author: Qi Zhao
Author-email: zhaoqi99@outlook.com
License: GPLv3
Platform: UNKNOWN
Classifier: License :: OSI Approved :: GNU General Public License v3 (GPLv3)
Classifier: Programming Language :: Python
Classifier: Programming Language :: Python :: 3
Classifier: Programming Language :: Python :: 3.5
Classifier: Programming Language :: Python :: 3.6
Classifier: Programming Language :: Python :: 3.7
Classifier: Programming Language :: Python :: Implementation :: CPython
Classifier: Programming Language :: Python :: Implementation :: PyPy
Requires-Python: >=3.0.0
